{
  "solution": {
    "create-release-plan-setup": {
      "impact": "minor",
      "oldVersion": "5.1.0",
      "newVersion": "5.2.0",
      "tagName": "latest",
      "constraints": [
        {
          "impact": "minor",
          "reason": "Appears in changelog section :rocket: Enhancement"
        },
        {
          "impact": "patch",
          "reason": "Appears in changelog section :bug: Bug Fix"
        }
      ],
      "pkgJSONPath": "./package.json"
    }
  },
  "description": "## Release (2026-01-14)\n\n* create-release-plan-setup 5.2.0 (minor)\n\n#### :rocket: Enhancement\n* `create-release-plan-setup`\n  * [#254](https://github.com/release-plan/create-release-plan-setup/pull/254) Update action versions ([@mansona](https://github.com/mansona))\n\n#### :bug: Bug Fix\n* `create-release-plan-setup`\n  * [#252](https://github.com/release-plan/create-release-plan-setup/pull/252) Move npm latest install outside of pnpm if ([@RobbieTheWagner](https://github.com/RobbieTheWagner))\n\n#### Committers: 2\n- Chris Manson ([@mansona](https://github.com/mansona))\n- Robbie Wagner ([@RobbieTheWagner](https://github.com/RobbieTheWagner))\n"
}
